ugly_bot/__init__.py
ugly_bot/bot.py
ugly_bot/bot_async.py
ugly_bot/bot_enums.py
ugly_bot/bot_types.py
ugly_bot-0.0.36.dist-info/licenses/LICENSE.txt
ugly_bot-0.0.36.dist-info/METADATA
ugly_bot-0.0.36.dist-info/WHEEL
ugly_bot-0.0.36.dist-info/top_level.txt
ugly_bot-0.0.36.dist-info/RECORD
