Metadata-Version: 2.4
Name: ugly_bot
Version: 0.0.36
Summary: Ugly is a platform for making amazing bots
Author-email: Justin Mann <justin.mann@gmail.com>
License: Copyright (c) 2018 The Python Packaging Authority
Project-URL: Homepage, https://ugly.bot
Project-URL: Issues, https://github.com/Effective-Nihilists/ugly_bot/issues
Project-URL: Documentation, https://docs.ugly.bot
Classifier: Programming Language :: Python :: 3
Classifier: Operating System :: OS Independent
Requires-Python: >=3.8
License-File: LICENSE.txt
Requires-Dist: python-socketio
Requires-Dist: websocket-client
Requires-Dist: requests
Requires-Dist: pydantic
Dynamic: license-file
